steelscript-2.0.1-py3.7-nspkg.pth
steelscript/commands/__init__.py
steelscript/commands/about.py
steelscript/commands/mkworkspace.py
steelscript/commands/rest.py
steelscript/commands/steel.py
steelscript/commands/test/__init__.py
steelscript/commands/test/test_install.py
steelscript/commands/test/test_mkworkspace.py
steelscript/commands/test/test_rest.py
steelscript/commands/test/test_steel.py
steelscript/common/__init__.py
steelscript/common/_fs.py
steelscript/common/api_helpers.py
steelscript/common/app.py
steelscript/common/connection.py
steelscript/common/datastructures.py
steelscript/common/datautils.py
steelscript/common/exceptions.py
steelscript/common/factory.py
steelscript/common/interval.py
steelscript/common/pkgutils.py
steelscript/common/polling.py
steelscript/common/service.py
steelscript/common/testrunner.py
steelscript/common/timeutils.py
steelscript/common/interaction/__init__.py
steelscript/common/interaction/action.py
steelscript/common/interaction/model.py
steelscript/common/interaction/uidelegation.py
steelscript/common/test/__init__.py
steelscript/common/test/test_interval.py
steelscript/common/test/test_jsondict.py
steelscript/common/test/test_steelscriptdir.py
steelscript/common/test/test_timerange.py
steelscript-2.0.1.dist-info/AUTHORS
steelscript-2.0.1.dist-info/LICENSE
steelscript-2.0.1.dist-info/METADATA
steelscript-2.0.1.dist-info/WHEEL
steelscript-2.0.1.dist-info/entry_points.txt
steelscript-2.0.1.dist-info/namespace_packages.txt
steelscript-2.0.1.dist-info/top_level.txt
steelscript-2.0.1.dist-info/RECORD
