Metadata-Version: 2.1
Name: steelscript
Version: 2.0.1
Summary: Core Python module for interacting with Riverbed devices
Home-page: http://pythonhosted.org/steelscript
Author: Riverbed Technology
Author-email: eng-github@riverbed.com
License: MIT
Platform: Linux
Platform: Mac OS
Platform: Windows
Classifier: Development Status :: 4 - Beta
Classifier: Intended Audience :: Developers
Classifier: Intended Audience :: Information Technology
Classifier: Intended Audience :: System Administrators
Classifier: License :: OSI Approved :: MIT License
Classifier: Programming Language :: Python :: 3.5
Classifier: Topic :: System :: Networking
Requires-Python: >3.5.0
Requires-Dist: requests (>=2.21.0)
Requires-Dist: python-dateutil
Provides-Extra: all
Provides-Extra: dev
Requires-Dist: pytest ; extra == 'dev'
Requires-Dist: testfixtures ; extra == 'dev'
Requires-Dist: mock ; extra == 'dev'
Requires-Dist: sphinx ; extra == 'dev'
Requires-Dist: sphinx-rtd-theme ; extra == 'dev'
Provides-Extra: doc
Requires-Dist: sphinx ; extra == 'doc'
Requires-Dist: sphinx-rtd-theme ; extra == 'doc'
Provides-Extra: test
Requires-Dist: pytest ; extra == 'test'
Requires-Dist: testfixtures ; extra == 'test'
Requires-Dist: mock ; extra == 'test'
